mozdevice/__init__.py
mozdevice/adb.py
mozdevice/adb_android.py
mozdevice/remote_process_monitor.py
mozdevice/version_codes.py
mozdevice-4.2.0.dist-info/METADATA
mozdevice-4.2.0.dist-info/WHEEL
mozdevice-4.2.0.dist-info/top_level.txt
mozdevice-4.2.0.dist-info/RECORD
